typedargs/__init__.py
typedargs/annotate.py
typedargs/basic_structures.py
typedargs/doc_annotate.py
typedargs/doc_parser.py
typedargs/exceptions.py
typedargs/lint.py
typedargs/metadata.py
typedargs/shell.py
typedargs/terminal.py
typedargs/type_annotations_parser.py
typedargs/typeinfo.py
typedargs/utils.py
typedargs/version.py
typedargs/types/__init__.py
typedargs/types/basic_dict.py
typedargs/types/bool.py
typedargs/types/bytes.py
typedargs/types/float.py
typedargs/types/integer.py
typedargs/types/list.py
typedargs/types/map.py
typedargs/types/path.py
typedargs/types/string.py
typedargs-1.1.3.dist-info/LICENSE
typedargs-1.1.3.dist-info/METADATA
typedargs-1.1.3.dist-info/WHEEL
typedargs-1.1.3.dist-info/top_level.txt
typedargs-1.1.3.dist-info/RECORD
